{
    "total": 14,
    "success": true,
    "arrayData": [
        {
            "id": 1,
            "name": "公民素养66条测试题Ⅰ",
            "info": "此套试题是测试公民素养...",
            "author": "榆林市健教所",
            "url": "http://xiaotu.net/examjson/suyang66-1.json"
        },
        {
            "id": 2,
            "name": "公民素养66条测试题Ⅱ",
            "info": "此套试题是测试公民素养...",
            "author": "榆林市健教所",
            "url": "http://xiaotu.net/examjson/suyang66-2.json"
        },
        {
            "id": 3,
            "name": "医院健康教育“两率”调查试卷",
            "info": "此套试题是测试医院健康教育...",
            "author": "榆林市健教所",
            "url": "http://xiaotu.net/examjson/yiyuanlianglv-1.json"
        },
        {
            "id": 4,
            "name": "居民健康知识测试题",
            "info": "此套试题是测试居民健康知识...",
            "author": "榆林市健教所",
            "url": "http://xiaotu.net/examjson/juminjiankang-1.json"
        },
        {
            "id": 5,
            "name": "榆林市行业健康知识测试卷",
            "info": "此套试题是测试行业健康知识...",
            "author": "榆林市健教所",
            "url": "http://xiaotu.net/examjson/hangyeceshi-1.json"
        },
        {
            "id": 6,
            "name": "小学生健康教育“两率”问卷调查",
            "info": "此套试题是测试小学生健康教育...",
            "author": "榆林市健教所",
            "url": "http://xiaotu.net/examjson/xiaoxuelianglv-1.json"
        },
        {
            "id": 7,
            "name": "小学生健康知识测试题",
            "info": "此套试题是测试小学生健康知识...",
            "author": "榆林市健教所",
            "url": "http://xiaotu.net/examjson/xiaoxuejiankang-1.json"
        },
        {
            "id": 8,
            "name": "医院患者及家属健康知识测试题",
            "info": "此套试题是测试医院患者...",
            "author": "榆林市健教所",
            "url": "http://xiaotu.net/examjson/yihuanjiashu-1.json"
        },
        {
            "id": 9,
            "name": "中学健康教育“两率”调查试题",
            "info": "此套试题是测试中学健康教育...",
            "author": "榆林市健教所",
            "url": "http://xiaotu.net/examjson/zhongxueshenglianglv-1.json"
        },
        {
            "id": 10,
            "name": "中学生健康知识测试题",
            "info": "此套试题是测试中学生健康...",
            "author": "榆林市健教所",
            "url": "http://xiaotu.net/examjson/zhongxueshengjiankang-1.json"
        },
        {
            "id": 11,
            "name": "公民健康教育知识200问",
            "info": "此套试题是测试公民健康教育知识...",
            "author": "榆林市健教所",
            "url": "http://xiaotu.net/examjson/jiaoyu200.json"
        }
    ]
}